movie.py
movies.py
rating.py
tools.py
movies_lib-0.1.3.dist-info/METADATA
movies_lib-0.1.3.dist-info/WHEEL
movies_lib-0.1.3.dist-info/top_level.txt
movies_lib-0.1.3.dist-info/RECORD
