Metadata-Version: 2.1
Name: movies_lib
Version: 0.1.3
Summary: Либа для лабораторной работы
Author: Kirill
Author-email: kirillgrekhovodov@gmail.com.com
Classifier: Programming Language :: Python :: 3
Classifier: License :: OSI Approved :: MIT License
Classifier: Operating System :: OS Independent
Requires-Python: >=3.10
